LICENSE
README.md
setup.py
flask_jwt_auth/__init__.py
flask_jwt_auth/decorators.py
flask_jwt_auth/functions.py
simporter_e0967f3e095ce309.egg-info/PKG-INFO
simporter_e0967f3e095ce309.egg-info/SOURCES.txt
simporter_e0967f3e095ce309.egg-info/dependency_links.txt
simporter_e0967f3e095ce309.egg-info/requires.txt
simporter_e0967f3e095ce309.egg-info/top_level.txt