Metadata-Version: 2.1
Name: simporter-e0967f3e095ce309
Version: 0.1.2
Summary: Flask JWT auth utils
Home-page: https://github.com/Simporter/flask-jwt-auth
Author: Yaroslav Kikvadze
Author-email: yaroslav.k@simporter.com
License: MIT
Platform: UNKNOWN
Requires-Python: >=3.8
License-File: LICENSE
